utils/__init__.py
utils/anticaptcha.py
utils/patch.py
utils/recaptcha_solver.py
utils_whitetail-0.0.9.dist-info/LICENSE
utils_whitetail-0.0.9.dist-info/METADATA
utils_whitetail-0.0.9.dist-info/WHEEL
utils_whitetail-0.0.9.dist-info/top_level.txt
utils_whitetail-0.0.9.dist-info/RECORD
